
{
  "placeholderImages": [
    {
      "id": "product-1",
      "description": "Premium Velvet Lipstick Magenta",
      "imageUrl": "https://picsum.photos/seed/lip1/600/600",
      "imageHint": "lipstick makeup"
    },
    {
      "id": "product-2",
      "description": "Smoothing Face Foundation",
      "imageUrl": "https://picsum.photos/seed/face1/600/600",
      "imageHint": "foundation cosmetics"
    },
    {
      "id": "product-3",
      "description": "Volumizing Black Mascara",
      "imageUrl": "https://picsum.photos/seed/eye1/600/600",
      "imageHint": "mascara beauty"
    },
    {
      "id": "product-4",
      "description": "Glittering Nail Polish Set",
      "imageUrl": "https://picsum.photos/seed/nail1/600/600",
      "imageHint": "nail polish"
    },
    {
      "id": "product-5",
      "description": "Hydrating Rose Skin Cream",
      "imageUrl": "https://picsum.photos/seed/skin1/600/600",
      "imageHint": "skincare cream"
    },
    {
      "id": "product-6",
      "description": "Long-lasting Eyeliner Pen",
      "imageUrl": "https://picsum.photos/seed/eye2/600/600",
      "imageHint": "eyeliner makeup"
    },
    {
      "id": "product-7",
      "description": "Golden Glow Highlighter",
      "imageUrl": "https://picsum.photos/seed/glow1/600/600",
      "imageHint": "highlighter makeup"
    },
    {
      "id": "product-8",
      "description": "Matte Finish Setting Powder",
      "imageUrl": "https://picsum.photos/seed/powder1/600/600",
      "imageHint": "face powder"
    }
  ]
}
